Metadata-Version: 2.1
Name: odoo10-addon-shopinvader-locomotive-guest-mode
Version: 10.0.1.0.1
Summary: Shopinvader guest mode for locomotive
Home-page: https://acsone.eu/
Author: ACSONE SA/NV,Odoo Community Association (OCA)
Author-email: support@odoo-community.org
License: AGPL-3
Platform: UNKNOWN
Classifier: Programming Language :: Python
Classifier: Framework :: Odoo
Classifier: License :: OSI Approved :: GNU Affero General Public License v3
Requires-Python: ~=2.7
Requires-Dist: odoo10-addon-shopinvader-guest-mode
Requires-Dist: odoo10-addon-shopinvader-locomotive
Requires-Dist: odoo (<10.1dev,>=10.0)
